[
    {   "avatarIcon": "https://i.ibb.co/QPPbTKR/java.jpg",
        "userName": "Java", "handle": "Java", "_id":"dreamwho1" },
    {   "avatarIcon": "https://i.ibb.co/GHhdMcg/relativity-logo.png",
        "userName": "Relativity Space",
        "handle": "relativityspace", "_id":"dreamwho2" },
    {   "avatarIcon": "https://i.ibb.co/vD386xJ/virgin.png",
        "userName": "Virgin Galactic",
        "handle": "virgingalactic", "_id":"dreamwho3" },
    {   "avatarIcon": "https://i.ibb.co/KD672ms/nasa.png",
        "userName": "NASA", "handle": "NASA", "_id":"dreamwho4" },
    {   "avatarIcon": "https://i.ibb.co/Z1fhRPD/tesla.png",
        "userName": "Tesla", "handle": "Tesla", "_id":"dreamwho5" }
 ]
 
 